sedas_pyapi/__init__.py
sedas_pyapi/bulk_download.py
sedas_pyapi/sedas_api.py
sedas_pyapi-0.5.0.dist-info/LICENSE
sedas_pyapi-0.5.0.dist-info/METADATA
sedas_pyapi-0.5.0.dist-info/WHEEL
sedas_pyapi-0.5.0.dist-info/top_level.txt
sedas_pyapi-0.5.0.dist-info/RECORD
