Metadata-Version: 2.1
Name: sedas-pyapi
Version: 0.5.0
Summary: client library to easily access the SeDAS API
Home-page: https://github.com/SatelliteApplicationsCatapult/sedas_pyapi
Author: Emily Selwood
Author-email: emily.selwood@sa.catapult.org.uk
License: apache2
Keywords: SeDAS API Client
Platform: UNKNOWN
Classifier: Development Status :: 4 - Beta
Classifier: Intended Audience :: Developers
Classifier: Natural Language :: English
Classifier: Programming Language :: Python :: 3.7
License-File: LICENSE
Requires-Dist: requests
